denodo_webservice/__init__.py
denodo_webservice/denodo.py
denodo_webservice/py.typed
denodo_webservice/url.py
denodo_webservice-0.1.4.dist-info/METADATA
denodo_webservice-0.1.4.dist-info/WHEEL
denodo_webservice-0.1.4.dist-info/RECORD
