Metadata-Version: 2.4
Name: denodo_webservice
Version: 0.1.4
Summary: Add your description here
Author-email: David Gallay <david.gallay.96@gmail.com>, David Gallay <david.gallay@nagra.com>
Requires-Python: >=3.10
Requires-Dist: requests>=2.32.3
